[{"id": "_meta", "logo": "", "name": "Lunar Eclipse v1.6", "author": "Ekin"}, {"id": "grandmother"}, {"id": "pixie"}, {"id": "sailor"}, {"id": "chambermaid"}, {"id": "mathematician"}, {"id": "innkeeper"}, {"id": "lycanthrope"}, {"id": "savant"}, {"id": "artist"}, {"id": "tealady"}, {"id": "magician"}, {"id": "mayor"}, {"id": "cannibal"}, {"id": "goon"}, {"id": "barber"}, {"id": "lunatic"}, {"id": "puzzlemaster"}, {"id": "godfather"}, {"id": "devilsadvocate"}, {"id": "spy"}, {"id": "assassin"}, {"id": "marionette"}, {"id": "nodashii"}, {"id": "zombuul"}, {"id": "vigormortis"}]