[{"id": "_meta", "logo": "https://i.imgur.com/NkIyWLs.png", "name": "Up the Mountain", "author": "Jams"}, {"id": "pixie"}, {"id": "shugenja"}, {"id": "knight"}, {"id": "highpriestess"}, {"id": "sailor"}, {"id": "fortuneteller"}, {"id": "mathematician"}, {"id": "oracle"}, {"id": "monk"}, {"id": "savant"}, {"id": "engineer"}, {"id": "seamstress"}, {"id": "cannibal"}, {"id": "mutant"}, {"id": "plaguedoctor"}, {"id": "drunk"}, {"id": "barber"}, {"id": "harpy"}, {"id": "spy"}, {"id": "psychopath"}, {"id": "scarletwoman"}, {"id": "lleech"}, {"id": "vigormortis"}, {"id": "fanggu"}, {"id": "vortox"}]